setup.cfg
setup.py
TGInterface/ClientSide.py
TGInterface/ServerSide.py
TGInterface/__init__.py
TGInterface/helper.py
TGInterface.egg-info/PKG-INFO
TGInterface.egg-info/PKG-INFO~
TGInterface.egg-info/SOURCES.txt
TGInterface.egg-info/dependency_links.txt
TGInterface.egg-info/namespace_packages.txt
TGInterface.egg-info/not-zip-safe
TGInterface.egg-info/top_level.txt