Metadata-Version: 1.0
Name: TGInterface
Version: 0.2.4
Summary: Provides clients access to models and methods defined on a TurboGears server.
Home-page: http://pypi.python.org/pypi/TGInterface
Author: Sam Wright
Author-email: UNKNOWN
License: MIT
Platform: UNKNOWN
Classifier: Development Status :: 3 - Alpha
Classifier: Operating System :: OS Independent
Classifier: Programming Language :: Python
Classifier: Topic :: Software Development :: Libraries :: Python Modules
Classifier: Framework :: TurboGears
